{
  "navigation": {
    "home": "الرئيسية",
    "resources": "المصادر",
    "menuTitle": "القائمة", 
    "categories": {
      "educational": "المواد التعليمية",
      "scientific": "الأوراق العلمية",
      "literature": "الأدب"
    },
    "library": {
      "title": "المكتبة",
      "books": "الكتب",
      "research": "الأبحاث",
      "articles": "المقالات"
    },
    "about": "حول",
    "contact": "اتصل بنا"
  },
 "auth": {
    "login": "تسجيل الدخول",
    "signup": "إنشاء حساب",
    "profile": "الملف الشخصي",
    "username": "اسم المستخدم",
    "password": "كلمة المرور",
    "phone": "الهاتف",
    "logout": "تسجيل الخروج",
    "loginSuccess": "تم تسجيل الدخول بنجاح",
    "registerSuccess": "تم تسجيل المستخدم بنجاح",
    "invalidCredentials": "اسم المستخدم أو كلمة المرور غير صحيحة",
    "userNotFound": "المستخدم غير موجود",
    "usernameExists": "اسم المستخدم أو الهاتف موجود بالفعل"
  },
 "home": {
    "hero": {
      "title": "بوابتك إلى المعرفة الرقمية",
      "description": "الوصول إلى آلاف الكتب والمجلات والأوراق البحثية من دور النشر والمؤسسات الرائدة.",
      "explore": "استكشاف الآن",
      "learnMore": "اعرف المزيد"
    },
    "stats": {
      "books": "الكتب",
      "journals": "المجلات",
      "articles": "المقالات",
      "users": "المستخدمين"
    },
     "categories": {
      "title": "استكشاف الفئات",
      "description": "تصفح الفئات المختلفة لاكتشاف المحتوى الذي يناسب اهتماماتك."
    }

  },
      "categories": {
      "title": "الفئات المميزة",
      "description": "تصفح عبر مختلف الفئات المعرفية واستكشف المكتبة الرقمية.",
      "academic": {
        "title": "أكاديمي",
        "description": "وصول إلى مجموعة واسعة من الموارد الأكاديمية والمواد."
      },
      "research": {
        "title": "بحث",
        "description": "استكشاف أوراق البحث والمجلات والمقالات من مختلف المجالات."
      },
      "literature": {
        "title": "أدب",
        "description": "غص في الأدب الكلاسيكي والحديث من المؤلفين المشهورين."
      }
    },
  "search": {
    "title": "ابحث في المكتبة",
    "description": "ابحث عن الكتب والمجلات والمقالات والمزيد باستخدام خيارات البحث المتقدمة.",
    "placeholder": "ابحث عن الكتب أو المجلات أو المقالات",
    "categoryPlaceholder": "حدد الفئة",
    "categories": {
      "all": "جميع الفئات",
      "books": "كتب",
      "articles": "مقالات",
      "journals": "مجلات"
    },
    "button": "ابحث"
  },
  "common": {
    "logo": "المكتبة الرقمية الصومالية",
    "search": "بحث",
    "language": "اللغة",
    "theme": "المظهر"
  },
  "footer": {
    "about": {
      "title": "عن الشركة",
      "description": "تعرف على مهمتنا والخدمات التي نقدمها لمساعدتك في استكشاف عالم المعرفة."
    },
    "quickLinks": {
      "title": "روابط سريعة",
      "links": [
        { "label": "الرئيسية", "href": "/" },
        { "label": "الفئات", "href": "/categories" },
        { "label": "الموارد", "href": "/resources" },
        { "label": "اتصل بنا", "href": "/contact" }
      ]
    },
    "resources": {
      "title": "الموارد",
      "links": [
        { "label": "المكتبة", "href": "/library" },
        { "label": "الأسئلة الشائعة", "href": "/faq" },
        { "label": "مركز المساعدة", "href": "/help-center" }
      ]
    },
    "newsletter": {
      "title": "اشترك في نشرتنا الإخبارية",
      "description": "ابق على اطلاع بأحدث الأخبار والمقالات والموارد من خلال الاشتراك في نشرتنا الإخبارية.",
      "placeholder": "أدخل بريدك الإلكتروني",
      "button": "اشترك"
    },
    "copyright": "جميع الحقوق محفوظة."
  },
  "about": {
      "title": "تعرف على مهمتنا والخدمات التي نقدمها لمساعدتك في استكشاف عالم المعرفة."
},
"resources": {
    "title": "موارد المكتبة الرقمية",
    "filters": {
      "title": "التصفية",
      "category": "الفئة",
      "type": "نوع المورد",
      "year": "سنة النشر",
      "language": "اللغة",
      "apply": "تطبيق التصفية",
      "clear": "مسح التصفية",
      "searchPlaceholder": "البحث حسب العنوان أو المؤلف أو الكلمات المفتاحية..."
    },
    "details": {
      "abstract": "ملخص",
      "authors": "المؤلفون",
      "published": "تاريخ النشر",
      "category": "الفئة",
      "type": "النوع",
      "downloads": "التحميلات",
      "citations": "الاقتباسات",
      "keywords": "الكلمات المفتاحية",
      "doi": "معرف الوثيقة الرقمي",
      "publisher": "الناشر",
      "pages": "الصفحات",
      "download": "تحميل",
      "cite": "اقتباس",
      "share": "مشاركة",
      "relatedResources": "موارد ذات صلة"
    },
    "types": {
      "book": "كتاب",
      "paper": "ورقة بحثية",
      "article": "مقال",
      "thesis": "أطروحة"
    },
    "noResults": "لم يتم العثور على موارد تطابق معايير البحث",
    "loading": "جاري تحميل الموارد...",
    "error": "خطأ في تحميل الموارد. يرجى المحاولة مرة أخرى."
  }
}
